{
  "summary": {
    "totalComponents": 0,
    "totalDownloads": 0,
    "totalProjects": 0,
    "avgQualityScore": 0
  },
  "mostUsed": [],
  "recentlyAdded": [],
  "trending": [],
  "byCategory": {
    "ui": 0,
    "sections": 0,
    "layout": 0
  },
  "byFramework": {
    "react": 0,
    "vue": 0,
    "svelte": 0
  },
  "byFeature": {
    "responsive": 0,
    "darkMode": 0,
    "accessible": 0,
    "animated": 0
  },
  "qualityMetrics": {
    "avgAccessibility": 0,
    "avgTestCoverage": 0,
    "avgBundleSize": 0
  },
  "timeline": []
}
